uaip/__init__.py
uaip/cli.py
uaip/communications/__init__.py
uaip/communications/base.py
uaip/communications/error.py
uaip/communications/handshake.py
uaip/communications/messages.py
uaip/communications/stage.py
uaip/communications/state_input_required.py
uaip/communications/state_update.py
uaip/communications/task_result.py
uaip/communications/transition_result.py
uaip/core/__init__.py
uaip/core/actions.py
uaip/core/builtins.py
uaip/core/construct.py
uaip/core/registry.py
uaip/core/results.py
uaip/core/stage.py
uaip/core/state.py
uaip/core/state_manager.py
uaip/core/task.py
uaip/core/types.py
uaip/core/workflow.py
uaip/engine/__init__.py
uaip/engine/language_engine.py
uaip/engine/orchestrator.py
uaip/external/__init__.py
uaip/external/contracts.py
uaip/presentations/__init__.py
uaip/presentations/base.py
uaip/presentations/brief.py
uaip/presentations/comprehensive.py
uaip/presentations/state_input.py
uaip/protocols/__init__.py
uaip/protocols/mcp_adapter.py
uaip/serving/__init__.py
uaip/serving/endpoints.py
uaip/serving/manager.py
uaip/serving/mcp.py
uaip/serving/native_uaip.py
uaip/serving/server.py
uaip/templates/__init__.py
uaip/templates/mini_store/README.md
uaip/templates/mini_store/__init__.py
uaip/templates/mini_store/main.py
uaip/templates/mini_store/requirements.txt
uaip-0.1.7.dist-info/licenses/LICENSE
uaip-0.1.7.dist-info/METADATA
uaip-0.1.7.dist-info/WHEEL
uaip-0.1.7.dist-info/entry_points.txt
uaip-0.1.7.dist-info/top_level.txt
uaip-0.1.7.dist-info/RECORD
