Metadata-Version: 2.4
Name: uaip
Version: 0.1.7
Summary: Universal Agent Interactive Protocol - Python SDK with a declarative framework to build Agentic AI Services
License: # License
Project-URL: Homepage, https://github.com/concierge-hq/UAIP
Project-URL: Repository, https://github.com/concierge-hq/UAIP
Requires-Python: >=3.9
License-File: LICENSE
Requires-Dist: fastapi>=0.109.0
Requires-Dist: uvicorn>=0.27.0
Requires-Dist: pydantic>=2.0.0
Requires-Dist: pyyaml>=6.0.0
Requires-Dist: click>=8.0.0
Dynamic: license-file
